odoo10_addon_sale_stock_picking_blocking_proc_group_by_line-10.0.1.0.0.99.dev5-py3.8-nspkg.pth
odoo/addons/sale_stock_picking_blocking_proc_group_by_line/README.rst
odoo/addons/sale_stock_picking_blocking_proc_group_by_line/__init__.py
odoo/addons/sale_stock_picking_blocking_proc_group_by_line/__manifest__.py
odoo/addons/sale_stock_picking_blocking_proc_group_by_line/i18n/ca.po
odoo/addons/sale_stock_picking_blocking_proc_group_by_line/i18n/de.po
odoo/addons/sale_stock_picking_blocking_proc_group_by_line/i18n/es.po
odoo/addons/sale_stock_picking_blocking_proc_group_by_line/i18n/es_VE.po
odoo/addons/sale_stock_picking_blocking_proc_group_by_line/i18n/fi.po
odoo/addons/sale_stock_picking_blocking_proc_group_by_line/i18n/fr.po
odoo/addons/sale_stock_picking_blocking_proc_group_by_line/i18n/it.po
odoo/addons/sale_stock_picking_blocking_proc_group_by_line/i18n/nl.po
odoo/addons/sale_stock_picking_blocking_proc_group_by_line/i18n/nl_NL.po
odoo/addons/sale_stock_picking_blocking_proc_group_by_line/i18n/pt_BR.po
odoo/addons/sale_stock_picking_blocking_proc_group_by_line/i18n/ro.po
odoo/addons/sale_stock_picking_blocking_proc_group_by_line/i18n/sale_stock_picking_blocking_proc_group_by_line.pot
odoo/addons/sale_stock_picking_blocking_proc_group_by_line/i18n/sk.po
odoo/addons/sale_stock_picking_blocking_proc_group_by_line/i18n/sl.po
odoo/addons/sale_stock_picking_blocking_proc_group_by_line/i18n/tr.po
odoo/addons/sale_stock_picking_blocking_proc_group_by_line/i18n/tr_TR.po
odoo/addons/sale_stock_picking_blocking_proc_group_by_line/models/__init__.py
odoo/addons/sale_stock_picking_blocking_proc_group_by_line/models/sale_order.py
odoo/addons/sale_stock_picking_blocking_proc_group_by_line/static/description/icon.png
odoo10_addon_sale_stock_picking_blocking_proc_group_by_line-10.0.1.0.0.99.dev5.dist-info/METADATA
odoo10_addon_sale_stock_picking_blocking_proc_group_by_line-10.0.1.0.0.99.dev5.dist-info/WHEEL
odoo10_addon_sale_stock_picking_blocking_proc_group_by_line-10.0.1.0.0.99.dev5.dist-info/namespace_packages.txt
odoo10_addon_sale_stock_picking_blocking_proc_group_by_line-10.0.1.0.0.99.dev5.dist-info/top_level.txt
odoo10_addon_sale_stock_picking_blocking_proc_group_by_line-10.0.1.0.0.99.dev5.dist-info/RECORD
