Metadata-Version: 2.1
Name: odoo10-addon-sale-stock-picking-blocking-proc-group-by-line
Version: 10.0.1.0.0.99.dev5
Summary: Module that allows module sale_delivery_block to work with sale_procurement_group_by_line
Home-page: https://github.com/OCA/sale-workflow
Author: Eficent, Odoo Community Association (OCA)
Author-email: support@odoo-community.org
License: AGPL-3
Platform: UNKNOWN
Classifier: Programming Language :: Python
Classifier: Framework :: Odoo
Classifier: Framework :: Odoo :: 10.0
Classifier: License :: OSI Approved :: GNU Affero General Public License v3
Requires-Python: ~=2.7
Requires-Dist: odoo10-addon-sale-procurement-group-by-line
Requires-Dist: odoo10-addon-sale-stock-picking-blocking
Requires-Dist: odoo (<10.1dev,>=10.0)
